.gitignore
Dockerfile
LICENSE.txt
README.md
logo.svg
requirements.txt
setup.py
api_server/config.json
api_server/server.py
api_server/dataset/.gitignore
api_server/default_dataset/README
api_server/default_dataset/allbut.pl
api_server/default_dataset/mku.sh
api_server/default_dataset/u.data
api_server/default_dataset/u.genre
api_server/default_dataset/u.info
api_server/default_dataset/u.item
api_server/default_dataset/u.occupation
api_server/default_dataset/u.user
api_server/default_dataset/u1.base
api_server/default_dataset/u1.test
api_server/default_dataset/u2.base
api_server/default_dataset/u2.test
api_server/default_dataset/u3.base
api_server/default_dataset/u3.test
api_server/default_dataset/u4.base
api_server/default_dataset/u4.test
api_server/default_dataset/u5.base
api_server/default_dataset/u5.test
api_server/default_dataset/ua.base
api_server/default_dataset/ua.test
api_server/default_dataset/ub.base
api_server/default_dataset/ub.test
api_server/model/.gitignore
dataset/ml-100k/README
dataset/ml-100k/allbut.pl
dataset/ml-100k/mku.sh
dataset/ml-100k/u.data
dataset/ml-100k/u.genre
dataset/ml-100k/u.info
dataset/ml-100k/u.item
dataset/ml-100k/u.occupation
dataset/ml-100k/u.user
dataset/ml-100k/u1.base
dataset/ml-100k/u1.test
dataset/ml-100k/u2.base
dataset/ml-100k/u2.test
dataset/ml-100k/u3.base
dataset/ml-100k/u3.test
dataset/ml-100k/u4.base
dataset/ml-100k/u4.test
dataset/ml-100k/u5.base
dataset/ml-100k/u5.test
dataset/ml-100k/ua.base
dataset/ml-100k/ua.test
dataset/ml-100k/ub.base
dataset/ml-100k/ub.test
dataset/ml-1m/README
dataset/ml-1m/movies.dat
dataset/ml-1m/ratings.dat
dataset/ml-1m/users.dat
devel/kmodes.ipynb
examples/benchmark.py
examples/cold_start.py
examples/similar_item.py
examples/user_specific.py
examples_output/user_specific_plot.png
k8s/configmap.yaml
k8s/deployment.yaml
k8s/pv.yaml
k8s/service.yaml
kabirrec/__init__.py
kabirrec/recommendation_service.py
kabirrec/utils.py
kabirrec.egg-info/PKG-INFO
kabirrec.egg-info/SOURCES.txt
kabirrec.egg-info/dependency_links.txt
kabirrec.egg-info/requires.txt
kabirrec.egg-info/top_level.txt
kabirrec/surprise/similarities.c
