Metadata-Version: 2.1
Name: kabirrec
Version: 1.0.11
Summary: A recommendation system with cold start, similar items and user specific recommendation
Home-page: https://github.com/smohammadhejazi/recommendation-as-a-service
Author: Seyyed Mohammad Hejazi Hoseini
Author-email: smohammadhejazi78@gmail.com
License: MIT
Keywords: recommendation-service,recommendation-system,recommender-system
Classifier: Programming Language :: Python :: 3
Classifier: License :: OSI Approved :: MIT License
Classifier: Operating System :: OS Independent
Classifier: Intended Audience :: Education
Classifier: Intended Audience :: Science/Research
License-File: LICENSE.txt
